creative_assistant/__init__.py
creative_assistant/assistant.py
creative_assistant/chat_service.py
creative_assistant/llms.py
creative_assistant/logger.py
creative_assistant/repositories.py
creative_assistant/entrypoints/__init__.py
creative_assistant/entrypoints/cli.py
creative_assistant/entrypoints/server.py
creative_assistant/entrypoints/streamlit.py
creative_assistant/entrypoints/streamlit_app.py
creative_assistant/entrypoints/static/browser/favicon.ico
creative_assistant/entrypoints/static/browser/index.html
creative_assistant/entrypoints/static/browser/main-UUKTUZLC.js
creative_assistant/entrypoints/static/browser/polyfills-FFHMD2TL.js
creative_assistant/entrypoints/static/browser/styles-5INURTSO.css
creative_assistant/models/chat.py
creative_assistant/models/entity.py
creative_assistant-0.5.1.dist-info/METADATA
creative_assistant-0.5.1.dist-info/WHEEL
creative_assistant-0.5.1.dist-info/entry_points.txt
creative_assistant-0.5.1.dist-info/top_level.txt
creative_assistant-0.5.1.dist-info/RECORD
