Metadata-Version: 2.4
Name: creative-assistant
Version: 0.5.1
Author-email: "Google Inc. (gTech gPS CSE team)" <no-reply@google.com>
License: Apache 2.0
Classifier: Development Status :: 4 - Beta
Classifier: Programming Language :: Python
Requires-Python: >=3.8
Requires-Dist: pydantic==2.9.2
Requires-Dist: langchain_google_vertexai
Requires-Dist: langchain
Requires-Dist: langchain_core
Requires-Dist: langchain_community
Provides-Extra: tagging
Requires-Dist: media-tagging[all]; extra == "tagging"
Provides-Extra: categorization
Requires-Dist: text-categorization; extra == "categorization"
Provides-Extra: server
Requires-Dist: fastapi[standard]; extra == "server"
Provides-Extra: streamlit
Requires-Dist: streamlit; extra == "streamlit"
Provides-Extra: all
Requires-Dist: creative-assistant[categorization,tagging]; extra == "all"
